MANIFEST.in
requirements.txt
setup.py
siametrics/lc/utils/__init__.py
siametrics/lc/utils/pubsub.py
siametrics/lc/utils/service_url.py
siametrics/lc/utils/settings.py
siametrics/lc/utils/data_fetcher/__init__.py
siametrics/lc/utils/data_fetcher/retrieve_data.py
siametrics/lc/utils/data_fetcher/settings.py
siametrics/lc/utils/data_fetcher/upload_data.py
siametrics/lc/utils/data_fetcher/utils.py
siametrics_lc_utils.egg-info/PKG-INFO
siametrics_lc_utils.egg-info/SOURCES.txt
siametrics_lc_utils.egg-info/dependency_links.txt
siametrics_lc_utils.egg-info/requires.txt
siametrics_lc_utils.egg-info/top_level.txt