Metadata-Version: 1.2
Name: siametrics-lc-utils
Version: 0.0.26
Summary: Siametrics Logistics Core Utils
Home-page: UNKNOWN
Author: SSripilaipong
Author-email: santhapon.s@siametrics.com
License: Apache 2.0
Platform: UNKNOWN
Requires-Python: >=3.7
